bmy/__init__.py
mlib/__init__.py
mlib/fs/__init__.py
mlib/py/__init__.py
mlib/py/test/__init__.py
mlib/py/test/support/__init__.py
mlib/sh/__init__.py
mplugins/myrrhc/alias_ext.py
mplugins/myrrhc/bmy_ext.py
mplugins/myrrhc/man_ext.py
mplugins/myrrhc/provider_ext.py
mplugins/myrrhc/myrrhc_ext/alias_ext.py
mplugins/myrrhc/myrrhc_ext/bmy_ext.py
mplugins/myrrhc/myrrhc_ext/man_ext.py
mplugins/provider/local/__init__.py
mplugins/provider/local/local_provider_ext.py
mplugins/provider/local/provider_ext.py
mplugins/provider/local/system.py
mpython/__init__.py
myrrh/__doc__.py
myrrh/__init__.py
myrrh/__license__.py
myrrh/__version__.py
myrrh/core/__init__.py
myrrh/core/_entity/__init__.py
myrrh/core/_entity/_entity.py
myrrh/core/_entity/_registry.py
myrrh/core/_entity/_services.py
myrrh/core/_system/__init__.py
myrrh/core/_system/managers/__init__.py
myrrh/core/_system/managers/_cache_mgr.py
myrrh/core/_system/managers/_object_mgr.py
myrrh/core/_system/managers/_task_mgr.py
myrrh/core/_system/objects/__init__.py
myrrh/core/_system/objects/_environment.py
myrrh/core/_system/objects/_exceptions.py
myrrh/core/_system/objects/_handle.py
myrrh/core/_system/objects/_io.py
myrrh/core/_system/objects/_objects.py
myrrh/core/_system/objects/_pipe.py
myrrh/core/_system/objects/_process.py
myrrh/core/_system/objects/_task.py
myrrh/core/_system/runtime/__init__.py
myrrh/core/_system/runtime/_runtime.py
myrrh/core/_system/runtime/_syscall.py
myrrh/core/interfaces/__init__.py
myrrh/core/interfaces/_delegation.py
myrrh/core/interfaces/_ientity.py
myrrh/core/interfaces/_isystem.py
myrrh/core/services/__init__.py
myrrh/core/services/entity.py
myrrh/core/services/groups.py
myrrh/core/services/logging.py
myrrh/core/services/system.py
myrrh/factory/__init__.py
myrrh/factory/_assembly.py
myrrh/framework/__init__.py
myrrh/framework/arch/__init__.py
myrrh/framework/arch/android/__init__.py
myrrh/framework/arch/android/myrrhos.py
myrrh/framework/arch/android/mfs/__init__.py
myrrh-0.1.0.dist-info/AUTHORS.md
myrrh-0.1.0.dist-info/LICENSE
myrrh-0.1.0.dist-info/METADATA
myrrh-0.1.0.dist-info/WHEEL
myrrh-0.1.0.dist-info/entry_points.txt
myrrh-0.1.0.dist-info/top_level.txt
myrrh-0.1.0.dist-info/RECORD
