Metadata-Version: 2.1
Name: myrrh
Version: 0.1.0
Summary: Myrrh is a Python development framework design to facilitate cloud processing and automation
Author-email: PyAnjel7 <pyanjel7@gmail.com>
License: GNU GENERAL PUBLIC LICENSE
Project-URL: Source, https://github.com/pyanjel7/myrrh_core
Classifier: Development Status :: 2 - Pre-Alpha
Classifier: Operating System :: Microsoft :: Windows
Classifier: Operating System :: POSIX
Classifier: Programming Language :: Python :: 3.11
Classifier: License :: OSI Approved :: GNU General Public License v3 or later (GPLv3+)
Classifier: Intended Audience :: Developers
Classifier: Intended Audience :: System Administrators
Classifier: Topic :: Software Development :: Libraries :: Python Modules
Classifier: Topic :: Software Development :: Testing
Classifier: Topic :: System :: Clustering
Classifier: Topic :: System :: Distributed Computing
Classifier: Topic :: System :: Monitoring
Classifier: Topic :: System :: Networking
Requires-Python: >=3.11.0
License-File: LICENSE
License-File: AUTHORS.md
Requires-Dist: colorama >=0.4
Requires-Dist: click >=8.1.2
Requires-Dist: prompt-toolkit >=3.0
Requires-Dist: ptpython >=3.0
Requires-Dist: textfsm >=1.1.2
Requires-Dist: pdoc >=10.0.4
Requires-Dist: pydantic >=2.4
Requires-Dist: cryptography >=41.0.1
